graphdoc/__init__.py
graphdoc/definitions.py
graphdoc/filters.py
graphdoc/render.py
graphdoc/utilities.py
graphdoc/templates/about.html
graphdoc/templates/enums.html
graphdoc/templates/index.html
graphdoc/templates/input_objects.html
graphdoc/templates/interfaces.html
graphdoc/templates/mutations.html
graphdoc/templates/objects.html
graphdoc/templates/queries.html
graphdoc/templates/scalars.html
graphdoc/templates/unions.html
tests/__init__.py
tests/common/__init__.py
tests/common/test_build_types_reference.py
tests/common/test_to_doc.py
tests/graphene_2/__init__.py
tests/graphene_2/test_utilities.py
tests/graphene_3/__init__.py
tests/graphene_3/test_utilities.py
graphdoc-0.4.0.dist-info/LICENSE
graphdoc-0.4.0.dist-info/METADATA
graphdoc-0.4.0.dist-info/WHEEL
graphdoc-0.4.0.dist-info/top_level.txt
graphdoc-0.4.0.dist-info/RECORD
