Metadata-Version: 2.1
Name: graphdoc
Version: 0.4.0
Summary: Generate HTML docs for your GraphQL API
Home-page: https://github.com/wallee94/graphdoc
Author: Walther Lee
Author-email: walthere.lee@gmail.com
License: UNKNOWN
Platform: UNKNOWN
Classifier: Programming Language :: Python :: 3
Classifier: License :: OSI Approved :: MIT License
Classifier: Operating System :: OS Independent
Requires-Python: >=3.6
Requires-Dist: graphql-core (<4,>=2.1.0)
Requires-Dist: Jinja2 (>=2)
Requires-Dist: markdown2 (>=2)
